vencopy/__init__.py
vencopy/__main__.py
vencopy/__run.py
vencopy/config/dev_config.yaml
vencopy/config/metadata.yaml
vencopy/config/metadata_default.yaml
vencopy/config/user_config.yaml.default
vencopy/core/__init__.py
vencopy/core/diarybuilders.py
vencopy/core/flexestimators.py
vencopy/core/gridmodellers.py
vencopy/core/postprocessors.py
vencopy/core/profileaggregators.py
vencopy/core/dataparsers/__init__.py
vencopy/core/dataparsers/dataparsers.py
vencopy/core/dataparsers/parkinference.py
vencopy/core/dataparsers/parseKiD.py
vencopy/core/dataparsers/parseMiD.py
vencopy/core/dataparsers/parseVF.py
vencopy/input/workflows_default.csv
vencopy/utils/__init__.py
vencopy/utils/metadata.py
vencopy/utils/utils.py
vencopy-1.0.6.dist-info/METADATA
vencopy-1.0.6.dist-info/WHEEL
vencopy-1.0.6.dist-info/licenses/LICENSE
vencopy-1.0.6.dist-info/RECORD
