Metadata-Version: 2.3
Name: vencopy
Version: 1.0.6
Summary: Vehicle Energy Consumption in Python: A tool to simulate load flexibility of electric vehicle fleets.
Project-URL: Homepage, https://gitlab.com/dlr-ve/esy/vencopy/vencopy
Project-URL: Documentation, https://dlr-ve.gitlab.io/esy/vencopy/vencopy/index.html
Project-URL: Repository, https://gitlab.com/dlr-ve/esy/vencopy/vencopy.git
Project-URL: Gitter, https://gitter.im/vencopy/community
Author-email: Fabia Miorelli <fabia.miorelli@dlr.de>, Niklas Wulff <niklas.wulff@dlr.de>
Classifier: Development Status :: 5 - Production/Stable
Classifier: Intended Audience :: Science/Research
Classifier: License :: OSI Approved :: BSD License
Classifier: Operating System :: Microsoft :: Windows
Classifier: Operating System :: Unix
Classifier: Programming Language :: Python
Classifier: Programming Language :: Python :: 3
Classifier: Programming Language :: Python :: 3.9
Classifier: Programming Language :: Python :: 3.10
Classifier: Programming Language :: Python :: 3.11
Classifier: Programming Language :: Python :: 3.12
Classifier: Topic :: Scientific/Engineering
Requires-Python: >=3.9
Requires-Dist: click
Requires-Dist: matplotlib
Requires-Dist: numpy
Requires-Dist: pandas
Requires-Dist: pyyaml
Requires-Dist: scipy
Provides-Extra: dev
Requires-Dist: black; extra == 'dev'
Provides-Extra: docs
Requires-Dist: rst2pdf; extra == 'docs'
Requires-Dist: sphinx; extra == 'docs'
Requires-Dist: sphinx-rtd-theme; extra == 'docs'
Provides-Extra: test
Requires-Dist: coverage; extra == 'test'
Requires-Dist: pytest; extra == 'test'
Requires-Dist: pytest-cov; extra == 'test'
